sapphirepy/__init__.py
sapphirepy/deoxysii.py
sapphirepy/envelope.py
sapphirepy/error.py
sapphirepy/sapphire.py
oasis_sapphire_py-0.4.0.dist-info/METADATA
oasis_sapphire_py-0.4.0.dist-info/WHEEL
oasis_sapphire_py-0.4.0.dist-info/top_level.txt
oasis_sapphire_py-0.4.0.dist-info/zip-safe
oasis_sapphire_py-0.4.0.dist-info/RECORD
