Metadata-Version: 2.4
Name: oasis-sapphire-py
Version: 0.4.0
Summary: Oasis Sapphire encryption middleware for Web3.py
Home-page: https://github.com/oasisprotocol/sapphire-paratime
Author: oasisprotocol
Author-email: team@oasisprotocol.org
License: Apache Software License 2.0
Classifier: Development Status :: 3 - Alpha
Classifier: Intended Audience :: Developers
Classifier: License :: OSI Approved :: Apache Software License
Classifier: Natural Language :: English
Classifier: Programming Language :: Python :: 3 :: Only
Classifier: Operating System :: OS Independent
Classifier: Typing :: Typed
Requires-Python: >=3.8
Requires-Dist: cbor2
Requires-Dist: pynacl
Requires-Dist: web3==7.*
Dynamic: author
Dynamic: author-email
Dynamic: classifier
Dynamic: description
Dynamic: description-content-type
Dynamic: home-page
Dynamic: license
Dynamic: requires-dist
Dynamic: requires-python
Dynamic: summary
